README.rst
setup.py
mail_alert/__init__.py
mail_alert/mail_alert.py
mail_alert.egg-info/PKG-INFO
mail_alert.egg-info/SOURCES.txt
mail_alert.egg-info/dependency_links.txt
mail_alert.egg-info/top_level.txt