Metadata-Version: 1.0
Name: mail-alert
Version: 0.0.1
Summary: monitor project and send email when errors occur
Home-page: UNKNOWN
Author: yaolu
Author-email: yaolu0405@gmail.com
License: MIT Licence
Keywords: pip,email
Platform: any
